jsonapi_pydantic/__init__.py
jsonapi_pydantic/constants.py
jsonapi_pydantic/utils.py
jsonapi_pydantic/v1_0/__init__.py
jsonapi_pydantic/v1_0/error.py
jsonapi_pydantic/v1_0/jsonapi.py
jsonapi_pydantic/v1_0/links.py
jsonapi_pydantic/v1_0/meta.py
jsonapi_pydantic/v1_0/resource/__init__.py
jsonapi_pydantic/v1_0/resource/relationship.py
jsonapi_pydantic/v1_0/resource/relationship_links.py
jsonapi_pydantic/v1_0/resource/resource.py
jsonapi_pydantic/v1_0/resource_identifier.py
jsonapi_pydantic/v1_0/toplevel.py
jsonapi_pydantic-0.2.5.dist-info/METADATA
jsonapi_pydantic-0.2.5.dist-info/WHEEL
jsonapi_pydantic-0.2.5.dist-info/RECORD
