Metadata-Version: 2.1
Name: jsonapi-pydantic
Version: 0.2.5
Summary: JSON:API implementation with pydantic.
Home-page: https://github.com/impocode/jsonapi-pydantic
License: MIT
Keywords: jsonapi,pydantic
Author: impocode
Author-email: impocode@impocode.one
Maintainer: impocode
Maintainer-email: impocode@impocode.one
Requires-Python: >=3.8.1,<4.0.0
Classifier: License :: OSI Approved :: MIT License
Classifier: Programming Language :: Python :: 3
Classifier: Programming Language :: Python :: 3.9
Classifier: Programming Language :: Python :: 3.10
Classifier: Programming Language :: Python :: 3.11
Classifier: Programming Language :: Python :: 3.12
Classifier: Programming Language :: Python :: 3 :: Only
Classifier: Programming Language :: Python :: 3.8
Classifier: Typing :: Typed
Requires-Dist: pydantic (>=2.1.1,<3.0.0)
Project-URL: Bug Tracker, https://github.com/impocode/jsonapi-pydantic/issues
Project-URL: Documentation, https://github.com/impocode/jsonapi-pydantic
Project-URL: Repository, https://github.com/impocode/jsonapi-pydantic
